actfw/__init__.py
actfw/_version.py
actfw/application.py
actfw/capture.py
actfw/command_server.py
actfw/display.py
actfw/edid.py
actfw/application/__init__.py
actfw/capture/__init__.py
actfw/command_server/__init__.py
actfw/display/__init__.py
actfw/edid/__init__.py
actfw/task/__init__.py
actfw/task/consumer.py
actfw/task/isolated.py
actfw/task/pipe.py
actfw/task/producer.py
actfw/task/task.py
actfw/task/consumer/__init__.py
actfw/task/isolated/__init__.py
actfw/task/pipe/__init__.py
actfw/task/producer/__init__.py
actfw/task/task/__init__.py
actfw/v4l2/__init__.py
actfw/v4l2/control.py
actfw/v4l2/types.py
actfw/v4l2/video.py
actfw/v4l2/control/__init__.py
actfw/v4l2/types/__init__.py
actfw/v4l2/video/__init__.py
actfw/vc4/__init__.py
actfw/vc4/display.py
actfw-1.4.0.dist-info/LICENSE.txt
actfw-1.4.0.dist-info/METADATA
actfw-1.4.0.dist-info/WHEEL
actfw-1.4.0.dist-info/top_level.txt
actfw-1.4.0.dist-info/RECORD
