Metadata-Version: 2.1
Name: actfw
Version: 1.4.0
Summary: *DEPRECATED* Actcast Application Framework
Home-page: https://github.com/Idein/actcast-app-python
Author: Idein Inc.
Author-email: n.ohkawa@idein.jp
License: MIT
Keywords: actcast
Platform: UNKNOWN
Classifier: Development Status :: 4 - Beta
Classifier: Intended Audience :: Developers
Classifier: License :: OSI Approved :: MIT License
Classifier: Programming Language :: Python :: 3 :: Only
Requires-Dist: actfw-raspberrypi
